{
  "main": {
    "id": "3a4c5dc91587959b",
    "type": "split",
    "children": [
      {
        "id": "0ae25b8142c87da6",
        "type": "tabs",
        "children": [
          {
            "id": "2a2008ebd58d730e",
            "type": "leaf",
            "state": {
              "type": "markdown",
              "state": {
                "file": "02_testing de la api.md",
                "mode": "source",
                "source": false
              }
            }
          },
          {
            "id": "a6563a2c30a150d6",
            "type": "leaf",
            "state": {
              "type": "markdown",
              "state": {
                "file": "03_dockerize rest01.md",
                "mode": "source",
                "source": false
              }
            }
          },
          {
            "id": "347deef82ab0061d",
            "type": "leaf",
            "state": {
              "type": "markdown",
              "state": {
                "file": "06_cloud deployment_fly.io.md",
                "mode": "source",
                "source": false
              }
            }
          },
          {
            "id": "7f7601b9b1e6fb08",
            "type": "leaf",
            "state": {
              "type": "markdown",
              "state": {
                "file": "07_cloud deployment_aws_ecs.md",
                "mode": "source",
                "source": false
              }
            }
          },
          {
            "id": "b752d2bbfde4d173",
            "type": "leaf",
            "state": {
              "type": "markdown",
              "state": {
                "file": "06_cloud deployment_fly.io.md",
                "mode": "source",
                "source": false
              }
            }
          },
          {
            "id": "12030a797c7370ab",
            "type": "leaf",
            "state": {
              "type": "image",
              "state": {
                "file": "images/Pasted image 20221118121911.png"
              }
            }
          },
          {
            "id": "ee1e0fa896197b45",
            "type": "leaf",
            "state": {
              "type": "markdown",
              "state": {
                "file": "10_cors en operaciones put y delete.md",
                "mode": "source",
                "source": false
              }
            }
          }
        ],
        "currentTab": 6
      }
    ],
    "direction": "vertical"
  },
  "left": {
    "id": "cddd33ef4ddc9b59",
    "type": "split",
    "children": [
      {
        "id": "cf625d4ea5228ec7",
        "type": "tabs",
        "children": [
          {
            "id": "cea36bcdeeb94beb",
            "type": "leaf",
            "state": {
              "type": "file-explorer",
              "state": {
                "sortOrder": "alphabetical"
              }
            }
          },
          {
            "id": "2312723228515858",
            "type": "leaf",
            "state": {
              "type": "search",
              "state": {
                "query": "",
                "matchingCase": false,
                "explainSearch": false,
                "collapseAll": false,
                "extraContext": false,
                "sortOrder": "alphabetical"
              }
            }
          },
          {
            "id": "cbed844d39f4c0c1",
            "type": "leaf",
            "state": {
              "type": "starred",
              "state": {}
            }
          }
        ]
      }
    ],
    "direction": "horizontal",
    "width": 300
  },
  "right": {
    "id": "c09f1db8703e1f0f",
    "type": "split",
    "children": [
      {
        "id": "babadc7d4079a9ea",
        "type": "tabs",
        "children": [
          {
            "id": "0d64811df0883ea5",
            "type": "leaf",
            "state": {
              "type": "backlink",
              "state": {
                "file": "10_cors en operaciones put y delete.md",
                "collapseAll": false,
                "extraContext": false,
                "sortOrder": "alphabetical",
                "showSearch": false,
                "searchQuery": "",
                "backlinkCollapsed": false,
                "unlinkedCollapsed": true
              }
            }
          },
          {
            "id": "ebd11b2f34961e5f",
            "type": "leaf",
            "state": {
              "type": "outgoing-link",
              "state": {
                "file": "10_cors en operaciones put y delete.md",
                "linksCollapsed": false,
                "unlinkedCollapsed": true
              }
            }
          },
          {
            "id": "417ff92a34d96ae4",
            "type": "leaf",
            "state": {
              "type": "tag",
              "state": {
                "sortOrder": "frequency",
                "useHierarchy": true
              }
            }
          },
          {
            "id": "25e9ab54283f293d",
            "type": "leaf",
            "state": {
              "type": "outline",
              "state": {
                "file": "10_cors en operaciones put y delete.md"
              }
            }
          }
        ]
      }
    ],
    "direction": "horizontal",
    "width": 300,
    "collapsed": true
  },
  "active": "ee1e0fa896197b45",
  "lastOpenFiles": [
    "02_testing de la api.md",
    "09_nodemessage_revert_commit_pushed.md",
    "images/Pasted image 20221117130104.png",
    "06_cloud deployment_fly.io.md",
    "08_cloud deployment_azure.md",
    "07_cloud deployment_aws_ecs.md",
    "03_dockerize rest01.md",
    "images/Pasted image 20221107140300.png",
    "images/Pasted image 20221107141039.png",
    "images/Pasted image 20221110121858.png"
  ]
}